FrequencyGenerator/FreqGenarator.py
FrequencyGenerator/__init__.py
FrequencyGenerator/about.py
FrequencyGenerator-0.1.dist-info/LICENSE
FrequencyGenerator-0.1.dist-info/METADATA
FrequencyGenerator-0.1.dist-info/WHEEL
FrequencyGenerator-0.1.dist-info/top_level.txt
FrequencyGenerator-0.1.dist-info/RECORD
